katdal/__init__.py
katdal/applycal.py
katdal/averager.py
katdal/categorical.py
katdal/chunkstore.py
katdal/chunkstore_dict.py
katdal/chunkstore_npy.py
katdal/chunkstore_s3.py
katdal/concatdata.py
katdal/dataset.py
katdal/datasources.py
katdal/flags.py
katdal/h5datav1.py
katdal/h5datav2.py
katdal/h5datav3.py
katdal/lazy_indexer.py
katdal/ms_async.py
katdal/ms_extra.py
katdal/sensordata.py
katdal/spectral_window.py
katdal/van_vleck.py
katdal/vis_flags_weights.py
katdal/visdatav4.py
katdal/test/__init__.py
katdal/test/conftest.py
katdal/test/s3_utils.py
katdal/test/test_applycal.py
katdal/test/test_categorical.py
katdal/test/test_chunkstore.py
katdal/test/test_chunkstore_dict.py
katdal/test/test_chunkstore_npy.py
katdal/test/test_chunkstore_s3.py
katdal/test/test_concatdata.py
katdal/test/test_dataset.py
katdal/test/test_datasources.py
katdal/test/test_lazy_indexer.py
katdal/test/test_sensordata.py
katdal/test/test_spectral_window.py
katdal/test/test_van_vleck.py
katdal/test/test_vis_flags_weights.py
katdal-0.23.data/scripts/mvf_copy.py
katdal-0.23.data/scripts/mvf_download.py
katdal-0.23.data/scripts/mvftoms.py
katdal-0.23.dist-info/LICENSE.txt
katdal-0.23.dist-info/METADATA
katdal-0.23.dist-info/WHEEL
katdal-0.23.dist-info/top_level.txt
katdal-0.23.dist-info/RECORD
