Metadata-Version: 2.1
Name: katdal
Version: 0.23
Summary: Karoo Array Telescope data access library for interacting with data sets in the MeerKAT Visibility Format (MVF)
Home-page: https://github.com/ska-sa/katdal
Author: Ludwig Schwardt
Author-email: ludwig@ska.ac.za
License: Modified BSD
Keywords: meerkat ska
Platform: OS Independent
Classifier: Development Status :: 4 - Beta
Classifier: Intended Audience :: Developers
Classifier: License :: OSI Approved :: BSD License
Classifier: Operating System :: OS Independent
Classifier: Programming Language :: Python
Classifier: Programming Language :: Python :: 3
Classifier: Topic :: Software Development :: Libraries :: Python Modules
Classifier: Topic :: Scientific/Engineering :: Astronomy
Requires-Python: >=3.6
License-File: LICENSE.txt
Requires-Dist: numpy >=1.12.0
Requires-Dist: katpoint <1,>=0.9
Requires-Dist: h5py >=2.3
Requires-Dist: numba
Requires-Dist: katsdptelstate[rdb] >=0.10
Requires-Dist: dask[array] >=2.7.0
Requires-Dist: requests >=2.18.0
Requires-Dist: pyjwt >=2
Requires-Dist: cityhash >=0.2.2
Requires-Dist: packaging
Provides-Extra: ms
Requires-Dist: python-casacore >=2.2.1 ; extra == 'ms'
Provides-Extra: s3
Provides-Extra: s3credentials
Requires-Dist: botocore ; extra == 's3credentials'
